aikido_zen/__init__.py
aikido_zen/api_discovery/README.md
aikido_zen/api_discovery/__init__.py
aikido_zen/api_discovery/get_api_info.py
aikido_zen/api_discovery/get_auth_types.py
aikido_zen/api_discovery/get_body_data_type.py
aikido_zen/api_discovery/get_data_schema.py
aikido_zen/api_discovery/is_primitive_type.py
aikido_zen/api_discovery/is_same_type.py
aikido_zen/api_discovery/merge_auth_types.py
aikido_zen/api_discovery/merge_data_schemas.py
aikido_zen/api_discovery/merge_types.py
aikido_zen/api_discovery/update_route_info.py
aikido_zen/aws_lambda/__init__.py
aikido_zen/background_process/__init__.py
aikido_zen/background_process/aikido_background_process.py
aikido_zen/background_process/api/__init__.py
aikido_zen/background_process/api/http_api.py
aikido_zen/background_process/api/http_api_ratelimited.py
aikido_zen/background_process/cloud_connection_manager/__init__.py
aikido_zen/background_process/cloud_connection_manager/get_manager_info.py
aikido_zen/background_process/cloud_connection_manager/on_detected_attack.py
aikido_zen/background_process/cloud_connection_manager/on_start.py
aikido_zen/background_process/cloud_connection_manager/send_heartbeat.py
aikido_zen/background_process/cloud_connection_manager/update_firewall_lists.py
aikido_zen/background_process/cloud_connection_manager/update_service_config.py
aikido_zen/background_process/commands/__init__.py
aikido_zen/background_process/commands/attack.py
aikido_zen/background_process/commands/check_firewall_lists.py
aikido_zen/background_process/commands/ping.py
aikido_zen/background_process/commands/read_property.py
aikido_zen/background_process/commands/should_ratelimit.py
aikido_zen/background_process/commands/sync_data.py
aikido_zen/background_process/comms.py
aikido_zen/background_process/heartbeats.py
aikido_zen/background_process/packages.py
aikido_zen/background_process/realtime/__init__.py
aikido_zen/background_process/realtime/start_polling_for_changes.py
aikido_zen-1.2.26.dist-info/METADATA
aikido_zen-1.2.26.dist-info/WHEEL
aikido_zen-1.2.26.dist-info/licenses/LICENSE
aikido_zen-1.2.26.dist-info/RECORD
